simplelpr/__init__.py
simplelpr/avcodec-61.dll
simplelpr/avformat-61.dll
simplelpr/avutil-59.dll
simplelpr/concrt140.dll
simplelpr/cudart64_12.dll
simplelpr/libSimpleLPR3.dll
simplelpr/msvcp140.dll
simplelpr/msvcp140_1.dll
simplelpr/msvcp140_2.dll
simplelpr/msvcp140_atomic_wait.dll
simplelpr/msvcp140_codecvt_ids.dll
simplelpr/onnxruntime.dll
simplelpr/opencv_calib3d971.dll
simplelpr/opencv_core971.dll
simplelpr/opencv_features2d971.dll
simplelpr/opencv_flann971.dll
simplelpr/opencv_imgcodecs971.dll
simplelpr/opencv_imgproc971.dll
simplelpr/pySimpleLPR3.cp310-win_amd64.pyd
simplelpr/pySimpleLPR3.cp311-win_amd64.pyd
simplelpr/pySimpleLPR3.cp312-win_amd64.pyd
simplelpr/pySimpleLPR3.cp313-win_amd64.pyd
simplelpr/pySimpleLPR3.cp314-win_amd64.pyd
simplelpr/pySimpleLPR3.cp38-win_amd64.pyd
simplelpr/pySimpleLPR3.cp39-win_amd64.pyd
simplelpr/runtime.lic
simplelpr/swresample-5.dll
simplelpr/swscale-8.dll
simplelpr/tbb12.dll
simplelpr/tbbmalloc.dll
simplelpr/vccorlib140.dll
simplelpr/vcomp140.dll
simplelpr/vcruntime140.dll
simplelpr/vcruntime140_1.dll
simplelpr/vcruntime140_threads.dll
simplelpr-3.6.3.dist-info/licenses/license.txt
simplelpr-3.6.3.dist-info/METADATA
simplelpr-3.6.3.dist-info/WHEEL
simplelpr-3.6.3.dist-info/top_level.txt
simplelpr-3.6.3.dist-info/RECORD
