Metadata-Version: 2.4
Name: SimpleLPR
Version: 3.6.3
Summary: SimpleLPR License Plate Recognition (LPR/ANPR) library.
Home-page: https://www.warelogic.com
Author: Xavier Girones
Author-email: xavier.girones@warelogic.com
Keywords: LPR,ANPR,SDK,toolkit,library,component,number plate recognition,license plate recognition,read license plates,read number plates,shareware
Classifier: Development Status :: 5 - Production/Stable
Classifier: Environment :: Console
Classifier: Environment :: Web Environment
Classifier: Intended Audience :: Developers
Classifier: License :: Other/Proprietary License
Classifier: Operating System :: Microsoft :: Windows
Classifier: Programming Language :: Python
Classifier: Topic :: Scientific/Engineering :: Image Recognition
Requires-Python: >=3.10, <3.15
License-File: license.txt
Dynamic: author
Dynamic: author-email
Dynamic: classifier
Dynamic: description
Dynamic: description-content-type
Dynamic: home-page
Dynamic: keywords
Dynamic: license-file
Dynamic: requires-python
Dynamic: summary
